nvisii-1.1.72.dist-info/RECORD
nvisii-1.1.72.dist-info/METADATA
nvisii-1.1.72.dist-info/top_level.txt
nvisii-1.1.72.dist-info/WHEEL
nvisii/__init__.py
nvisii/_nvisii.so
nvisii/importers/__init__.py
