Metadata-Version: 2.1
Name: nvisii
Version: 1.1.72
Summary: UNKNOWN
Home-page: UNKNOWN
Author: Nate Morrical
Author-email: 
Maintainer: 
Maintainer-email: 
License: UNKNOWN
Platform: UNKNOWN
Requires-Python: >=3.6
Requires-Dist: numpy (>=1.19.5)
